quickdone/__init__.py
quickdone/quickdone.py
quickdone/rython.py
quickdone-0.0.14.dist-info/LICENSE
quickdone-0.0.14.dist-info/METADATA
quickdone-0.0.14.dist-info/WHEEL
quickdone-0.0.14.dist-info/top_level.txt
quickdone-0.0.14.dist-info/RECORD
