Metadata-Version: 2.1
Name: quickdone
Version: 0.0.14
Summary: A handy toolkit
Home-page: https://github.com/donequick/quickdone
Author: quickdone
Author-email: donequick@outlook.com
License: UNKNOWN
Platform: UNKNOWN
Classifier: Programming Language :: Python :: 3
Classifier: License :: OSI Approved :: GNU Affero General Public License v3 or later (AGPLv3+)
Classifier: Operating System :: POSIX :: Linux
Requires-Python: >=3.7.2
Requires-Dist: xlrd
Requires-Dist: pandas
